README.md
setup.py
nzl_tool/__init__.py
nzl_tool.egg-info/PKG-INFO
nzl_tool.egg-info/SOURCES.txt
nzl_tool.egg-info/dependency_links.txt
nzl_tool.egg-info/top_level.txt
nzl_tool/encrypt/AESUtils.py
nzl_tool/encrypt/DesUtils.py
nzl_tool/encrypt/__init__.py
nzl_tool/jwt/__init__.py
nzl_tool/jwt/_json.py
nzl_tool/jwt/encoding.py
nzl_tool/jwt/exc.py
nzl_tool/jwt/jws.py
nzl_tool/jwt/serializer.py
nzl_tool/jwt/signer.py
nzl_tool/jwt/timed.py
nzl_tool/jwt/url_safe.py
nzl_tool/mysql/__init__.py
nzl_tool/mysql/mysql_tools.py